tw/_C.cpython-37m-darwin.so
tw/__init__.py
tw/app/__init__.py
tw/app/context.py
tw/app/defaults.py
tw/app/dist.py
tw/app/entrance.py
tw/app/launch.py
tw/convertor/Tensor.py
tw/convertor/TensorMap.py
tw/convertor/__init__.py
tw/convertor/pytorch.py
tw/nn/__init__.py
tw/nn/layer/__init__.py
tw/nn/layer/empty_op.py
tw/nn/layer/frozen_batch_norm.py
tw/nn/layer/l2_norm.py
tw/nn/layer/multiclass_nms.py
tw/nn/layer/nms.py
tw/nn/layer/rnn.py
tw/nn/layer/rnn_test.py
tw/nn/layer/roi_align.py
tw/nn/layer/roi_pool.py
tw/nn/layer/sigmoid_focal_loss.py
tw/nn/layer/yolo_layer.py
tw/nn/loss/__init__.py
tw/nn/loss/smooth_l1_loss.py
tw/nn/metric/__init__.py
tw/nn/metric/regression.py
tw/nn/metric/top_k.py
tw/solver/__init__.py
tw/solver/checkpoint.py
tw/solver/convertor.py
tw/solver/solver.py
tw/solver/warmup_multistep_lr.py
tw/transform/__init__.py
tw/transform/image.py
tw/utils/__init__.py
tw/utils/device.py
tw/utils/filesystem.py
tw/utils/kv.py
tw/utils/logger.py
tw/utils/parser.py
tw/utils/stats.py
tw/utils/string.py
tw/utils/viz.py
tw-0.3.0.dist-info/LICENSE
tw-0.3.0.dist-info/METADATA
tw-0.3.0.dist-info/WHEEL
tw-0.3.0.dist-info/top_level.txt
tw-0.3.0.dist-info/RECORD
